yorkmcp/__init__.py
yorkmcp-0.1.4.dist-info/METADATA
yorkmcp-0.1.4.dist-info/WHEEL
yorkmcp-0.1.4.dist-info/entry_points.txt
yorkmcp-0.1.4.dist-info/RECORD
