Metadata-Version: 2.4
Name: yorkmcp
Version: 0.1.4
Summary: Add your description here
Requires-Python: >=3.11
Requires-Dist: mcp[cli]>=1.9.4
